pyrolysate/__init__.py
pyrolysate/cli.py
pyrolysate/common.py
pyrolysate/converter_async.py
pyrolysate/email_parser.py
pyrolysate/tld.txt
pyrolysate/update_tlds.py
pyrolysate/url_parser.py
pyrolysate/utils.py
pyrolysate-1.0.0.dist-info/METADATA
pyrolysate-1.0.0.dist-info/WHEEL
pyrolysate-1.0.0.dist-info/entry_points.txt
pyrolysate-1.0.0.dist-info/licenses/LICENSE
pyrolysate-1.0.0.dist-info/RECORD
