Metadata-Version: 2.4
Name: pyrolysate
Version: 1.0.0
Summary: Parser made to convert lists of emails and urls into JSON formatted, CSV formatted, or plain text strings or files
Project-URL: Homepage, https://github.com/dawnandrew100/pyrolysate
Project-URL: Issues, https://github.com/dawnandrew100/pyrolysate/issues
Author-email: Andrew Hennis <andrew.mr.hennis@gmail.com>
License-File: LICENSE
Classifier: License :: OSI Approved :: MIT License
Classifier: Operating System :: OS Independent
Classifier: Programming Language :: Python :: 3
Requires-Python: >=3.10
